datamotion_securemessaging/SecureMessaging.py
datamotion_securemessaging/UnitTesting.py
datamotion_securemessaging/__init__.py
datamotion_securemessaging/Models/Accounts.py
datamotion_securemessaging/Models/Folders.py
datamotion_securemessaging/Models/Messages.py
datamotion_securemessaging/Models/__init__.py
datamotion_securemessaging-1.0.0.dist-info/LICENSE.txt
datamotion_securemessaging-1.0.0.dist-info/METADATA
datamotion_securemessaging-1.0.0.dist-info/WHEEL
datamotion_securemessaging-1.0.0.dist-info/top_level.txt
datamotion_securemessaging-1.0.0.dist-info/RECORD
